setup.py
tox_pytest_summary.py
tox_pytest_summary.egg-info/PKG-INFO
tox_pytest_summary.egg-info/SOURCES.txt
tox_pytest_summary.egg-info/dependency_links.txt
tox_pytest_summary.egg-info/entry_points.txt
tox_pytest_summary.egg-info/requires.txt
tox_pytest_summary.egg-info/top_level.txt