Metadata-Version: 1.1
Name: tox-pytest-summary
Version: 0.1.2
Summary: Tox + Py.test summary
Home-page: https://github.com/FedericoCeratto/tox-pytest-summary
Author: Federico Ceratto
Author-email: federico.ceratto@gmail.com
License: AGPLv3
Platform: Linux
Classifier: Development Status :: 3 - Alpha
Classifier: Environment :: Console
Classifier: Intended Audience :: Developers
Classifier: License :: OSI Approved :: GNU Affero General Public License v3
Classifier: Natural Language :: English
Classifier: Operating System :: POSIX :: Linux
Classifier: Programming Language :: Python
Classifier: Programming Language :: Python :: 2
Classifier: Topic :: Software Development :: Testing
